ndx_tank_metadata/__init__.py
ndx_tank_metadata/maze_extension.py
ndx_tank_metadata/spec/ndx-tank-metadata.extensions.yaml
ndx_tank_metadata/spec/ndx-tank-metadata.namespace.yaml
ndx_tank_metadata-0.2.0.dist-info/LICENSE
ndx_tank_metadata-0.2.0.dist-info/METADATA
ndx_tank_metadata-0.2.0.dist-info/WHEEL
ndx_tank_metadata-0.2.0.dist-info/top_level.txt
ndx_tank_metadata-0.2.0.dist-info/RECORD
