Metadata-Version: 2.1
Name: ndx-tank-metadata
Version: 0.2.0
Summary: NWB:N extension for storing metadata for Tank lab
Home-page: https://github.com/catalystneuro/ndx-tank-metadata
Author: Szonja Weigl, Luiz Tauffer and Ben Dichter
Author-email: ben.dichter@gmail.com
License: UNKNOWN
Platform: UNKNOWN
Requires-Dist: pynwb (>=1.4.0)
